MANIFEST.in
README.md
setup.cfg
setup.py
ub_paste/__init__.py
ub_paste/language_map.py
ub_paste/ub_paste.py
ub_paste.egg-info/PKG-INFO
ub_paste.egg-info/SOURCES.txt
ub_paste.egg-info/dependency_links.txt
ub_paste.egg-info/entry_points.txt
ub_paste.egg-info/not-zip-safe
ub_paste.egg-info/requires.txt
ub_paste.egg-info/top_level.txt