Metadata-Version: 1.1
Name: ub-paste
Version: 0.1.0
Summary: Help you paste your file content to ubuntu pastebin
Home-page: https://github.com/lazzzis/ub-paste
Author: lazzzis
Author-email: shenlijin@outlook.com
License: MIT
Platform: any
Classifier: License :: OSI Approved :: MIT License
Classifier: Operating System :: OS Independent
Classifier: Programming Language :: Python
Classifier: Topic :: Software Development :: Libraries :: Python Modules
Classifier: Intended Audience :: Developers
